[
  {
    "id": "2645cf99b94b2d0cc4ecbfed1cf56bdf",
    "sport_key": "basketball_nba",
    "sport_title": "NBA",
    "commence_time": "2025-12-31T01:11:00Z",
    "home_team": "Memphis Grizzlies",
    "away_team": "Philadelphia 76ers",
    "bookmakers": [
      {
        "key": "fanduel",
        "title": "FanDuel",
        "last_update": "2025-12-31T01:40:36Z",
        "markets": [
          {
            "key": "totals",
            "last_update": "2025-12-31T01:40:36Z",
            "outcomes": [
              {
                "name": "Over",
                "price": -114,
                "point": 247.5
              },
              {
                "name": "Under",
                "price": -114,
                "point": 247.5
              }
            ]
          }
        ]
      },
      {
        "key": "mybookieag",
        "title": "MyBookie.ag",
        "last_update": "2025-12-31T01:39:04Z",
        "markets": [
          {
            "key": "totals",
            "last_update": "2025-12-31T01:39:04Z",
            "outcomes": [
              {
                "name": "Over",
                "price": 100,
                "point": 250.5
              },
              {
                "name": "Under",
                "price": -125,
                "point": 250.5
              }
            ]
          }
        ]
      },
      {
        "key": "draftkings",
        "title": "DraftKings",
        "last_update": "2025-12-31T01:40:35Z",
        "markets": [
          {
            "key": "totals",
            "last_update": "2025-12-31T01:40:35Z",
            "outcomes": [
              {
                "name": "Over",
                "price": -120,
                "point": 245.5
              },
              {
                "name": "Under",
                "price": -110,
                "point": 245.5
              }
            ]
          }
        ]
      },
      {
        "key": "williamhill_us",
        "title": "Caesars",
        "last_update": "2025-12-31T01:37:44Z",
        "markets": [
          {
            "key": "totals",
            "last_update": "2025-12-31T01:37:44Z",
            "outcomes": [
              {
                "name": "Over",
                "price": -105,
                "point": 248.5
              },
              {
                "name": "Under",
                "price": -125,
                "point": 248.5
              }
            ]
          }
        ]
      },
      {
        "key": "fanatics",
        "title": "Fanatics",
        "last_update": "2025-12-31T01:40:35Z",
        "markets": [
          {
            "key": "totals",
            "last_update": "2025-12-31T01:40:35Z",
            "outcomes": [
              {
                "name": "Over",
                "price": -115,
                "point": 245.5
              },
              {
                "name": "Under",
                "price": -115,
                "point": 245.5
              }
            ]
          }
        ]
      },
      {
        "key": "bovada",
        "title": "Bovada",
        "last_update": "2025-12-31T01:40:35Z",
        "markets": [
          {
            "key": "totals",
            "last_update": "2025-12-31T01:40:35Z",
            "outcomes": [
              {
                "name": "Over",
                "price": -115,
                "point": 246.5
              },
              {
                "name": "Under",
                "price": -115,
                "point": 246.5
              }
            ]
          }
        ]
      },
      {
        "key": "betmgm",
        "title": "BetMGM",
        "last_update": "2025-12-31T01:40:20Z",
        "markets": [
          {
            "key": "totals",
            "last_update": "2025-12-31T01:40:20Z",
            "outcomes": [
              {
                "name": "Over",
                "price": -110,
                "point": 247.5
              },
              {
                "name": "Under",
                "price": -118,
                "point": 247.5
              }
            ]
          }
        ]
      }
    ]
  },
  {
    "id": "5748aa8ead4679a8d9afe966bc5e844b",
    "sport_key": "basketball_nba",
    "sport_title": "NBA",
    "commence_time": "2025-12-31T02:10:00Z",
    "home_team": "Utah Jazz",
    "away_team": "Boston Celtics",
    "bookmakers": [
      {
        "key": "fanduel",
        "title": "FanDuel",
        "last_update": "2025-12-31T01:40:36Z",
        "markets": [
          {
            "key": "totals",
            "last_update": "2025-12-31T01:40:36Z",
            "outcomes": [
              {
                "name": "Over",
                "price": -106,
                "point": 243.5
              },
              {
                "name": "Under",
                "price": -114,
                "point": 243.5
              }
            ]
          }
        ]
      },
      {
        "key": "betonlineag",
        "title": "BetOnline.ag",
        "last_update": "2025-12-31T01:40:09Z",
        "markets": [
          {
            "key": "totals",
            "last_update": "2025-12-31T01:40:09Z",
            "outcomes": [
              {
                "name": "Over",
                "price": -110,
                "point": 242.5
              },
              {
                "name": "Under",
                "price": -110,
                "point": 242.5
              }
            ]
          }
        ]
      },
      {
        "key": "lowvig",
        "title": "LowVig.ag",
        "last_update": "2025-12-31T01:40:36Z",
        "markets": [
          {
            "key": "totals",
            "last_update": "2025-12-31T01:40:36Z",
            "outcomes": [
              {
                "name": "Over",
                "price": -107,
                "point": 242.5
              },
              {
                "name": "Under",
                "price": -107,
                "point": 242.5
              }
            ]
          }
        ]
      },
      {
        "key": "mybookieag",
        "title": "MyBookie.ag",
        "last_update": "2025-12-31T01:39:04Z",
        "markets": [
          {
            "key": "totals",
            "last_update": "2025-12-31T01:39:04Z",
            "outcomes": [
              {
                "name": "Over",
                "price": -110,
                "point": 243.0
              },
              {
                "name": "Under",
                "price": -110,
                "point": 243.0
              }
            ]
          }
        ]
      },
      {
        "key": "draftkings",
        "title": "DraftKings",
        "last_update": "2025-12-31T01:40:35Z",
        "markets": [
          {
            "key": "totals",
            "last_update": "2025-12-31T01:40:35Z",
            "outcomes": [
              {
                "name": "Over",
                "price": -112,
                "point": 242.5
              },
              {
                "name": "Under",
                "price": -108,
                "point": 242.5
              }
            ]
          }
        ]
      },
      {
        "key": "williamhill_us",
        "title": "Caesars",
        "last_update": "2025-12-31T01:37:44Z",
        "markets": [
          {
            "key": "totals",
            "last_update": "2025-12-31T01:37:44Z",
            "outcomes": [
              {
                "name": "Over",
                "price": -110,
                "point": 242.5
              },
              {
                "name": "Under",
                "price": -110,
                "point": 242.5
              }
            ]
          }
        ]
      },
      {
        "key": "fanatics",
        "title": "Fanatics",
        "last_update": "2025-12-31T01:40:35Z",
        "markets": [
          {
            "key": "totals",
            "last_update": "2025-12-31T01:40:35Z",
            "outcomes": [
              {
                "name": "Over",
                "price": -110,
                "point": 243.0
              },
              {
                "name": "Under",
                "price": -110,
                "point": 243.0
              }
            ]
          }
        ]
      },
      {
        "key": "bovada",
        "title": "Bovada",
        "last_update": "2025-12-31T01:40:35Z",
        "markets": [
          {
            "key": "totals",
            "last_update": "2025-12-31T01:40:35Z",
            "outcomes": [
              {
                "name": "Over",
                "price": -110,
                "point": 243.0
              },
              {
                "name": "Under",
                "price": -110,
                "point": 243.0
              }
            ]
          }
        ]
      },
      {
        "key": "betus",
        "title": "BetUS",
        "last_update": "2025-12-31T01:40:49Z",
        "markets": [
          {
            "key": "totals",
            "last_update": "2025-12-31T01:40:49Z",
            "outcomes": [
              {
                "name": "Over",
                "price": -110,
                "point": 243.0
              },
              {
                "name": "Under",
                "price": -110,
                "point": 243.0
              }
            ]
          }
        ]
      },
      {
        "key": "betmgm",
        "title": "BetMGM",
        "last_update": "2025-12-31T01:40:20Z",
        "markets": [
          {
            "key": "totals",
            "last_update": "2025-12-31T01:40:20Z",
            "outcomes": [
              {
                "name": "Over",
                "price": -115,
                "point": 242.5
              },
              {
                "name": "Under",
                "price": -105,
                "point": 242.5
              }
            ]
          }
        ]
      }
    ]
  },
  {
    "id": "12a69f98068c9e1b277528c3f7dfed72",
    "sport_key": "basketball_nba",
    "sport_title": "NBA",
    "commence_time": "2025-12-31T03:40:00Z",
    "home_team": "Los Angeles Lakers",
    "away_team": "Detroit Pistons",
    "bookmakers": [
      {
        "key": "fanduel",
        "title": "FanDuel",
        "last_update": "2025-12-31T01:40:36Z",
        "markets": [
          {
            "key": "totals",
            "last_update": "2025-12-31T01:40:36Z",
            "outcomes": [
              {
                "name": "Over",
                "price": -108,
                "point": 233.5
              },
              {
                "name": "Under",
                "price": -112,
                "point": 233.5
              }
            ]
          }
        ]
      },
      {
        "key": "lowvig",
        "title": "LowVig.ag",
        "last_update": "2025-12-31T01:40:36Z",
        "markets": [
          {
            "key": "totals",
            "last_update": "2025-12-31T01:40:36Z",
            "outcomes": [
              {
                "name": "Over",
                "price": -107,
                "point": 233.0
              },
              {
                "name": "Under",
                "price": -107,
                "point": 233.0
              }
            ]
          }
        ]
      },
      {
        "key": "betonlineag",
        "title": "BetOnline.ag",
        "last_update": "2025-12-31T01:40:09Z",
        "markets": [
          {
            "key": "totals",
            "last_update": "2025-12-31T01:40:09Z",
            "outcomes": [
              {
                "name": "Over",
                "price": -110,
                "point": 233.0
              },
              {
                "name": "Under",
                "price": -110,
                "point": 233.0
              }
            ]
          }
        ]
      },
      {
        "key": "draftkings",
        "title": "DraftKings",
        "last_update": "2025-12-31T01:40:35Z",
        "markets": [
          {
            "key": "totals",
            "last_update": "2025-12-31T01:40:35Z",
            "outcomes": [
              {
                "name": "Over",
                "price": -115,
                "point": 232.5
              },
              {
                "name": "Under",
                "price": -105,
                "point": 232.5
              }
            ]
          }
        ]
      },
      {
        "key": "williamhill_us",
        "title": "Caesars",
        "last_update": "2025-12-31T01:37:44Z",
        "markets": [
          {
            "key": "totals",
            "last_update": "2025-12-31T01:37:44Z",
            "outcomes": [
              {
                "name": "Over",
                "price": -110,
                "point": 233.0
              },
              {
                "name": "Under",
                "price": -110,
                "point": 233.0
              }
            ]
          }
        ]
      },
      {
        "key": "fanatics",
        "title": "Fanatics",
        "last_update": "2025-12-31T01:40:35Z",
        "markets": [
          {
            "key": "totals",
            "last_update": "2025-12-31T01:40:35Z",
            "outcomes": [
              {
                "name": "Over",
                "price": -105,
                "point": 233.5
              },
              {
                "name": "Under",
                "price": -115,
                "point": 233.5
              }
            ]
          }
        ]
      },
      {
        "key": "bovada",
        "title": "Bovada",
        "last_update": "2025-12-31T01:40:35Z",
        "markets": [
          {
            "key": "totals",
            "last_update": "2025-12-31T01:40:35Z",
            "outcomes": [
              {
                "name": "Over",
                "price": -110,
                "point": 233.5
              },
              {
                "name": "Under",
                "price": -110,
                "point": 233.5
              }
            ]
          }
        ]
      },
      {
        "key": "mybookieag",
        "title": "MyBookie.ag",
        "last_update": "2025-12-31T01:39:04Z",
        "markets": [
          {
            "key": "totals",
            "last_update": "2025-12-31T01:39:04Z",
            "outcomes": [
              {
                "name": "Over",
                "price": -110,
                "point": 233.0
              },
              {
                "name": "Under",
                "price": -110,
                "point": 233.0
              }
            ]
          }
        ]
      },
      {
        "key": "betmgm",
        "title": "BetMGM",
        "last_update": "2025-12-31T01:40:20Z",
        "markets": [
          {
            "key": "totals",
            "last_update": "2025-12-31T01:40:20Z",
            "outcomes": [
              {
                "name": "Over",
                "price": -110,
                "point": 233.5
              },
              {
                "name": "Under",
                "price": -110,
                "point": 233.5
              }
            ]
          }
        ]
      },
      {
        "key": "betus",
        "title": "BetUS",
        "last_update": "2025-12-31T01:40:49Z",
        "markets": [
          {
            "key": "totals",
            "last_update": "2025-12-31T01:40:49Z",
            "outcomes": [
              {
                "name": "Over",
                "price": -110,
                "point": 233.0
              },
              {
                "name": "Under",
                "price": -110,
                "point": 233.0
              }
            ]
          }
        ]
      }
    ]
  },
  {
    "id": "80726b18a644735592fda8cea0575612",
    "sport_key": "basketball_nba",
    "sport_title": "NBA",
    "commence_time": "2025-12-31T04:10:00Z",
    "home_team": "Los Angeles Clippers",
    "away_team": "Sacramento Kings",
    "bookmakers": [
      {
        "key": "fanduel",
        "title": "FanDuel",
        "last_update": "2025-12-31T01:40:36Z",
        "markets": [
          {
            "key": "totals",
            "last_update": "2025-12-31T01:40:36Z",
            "outcomes": [
              {
                "name": "Over",
                "price": -112,
                "point": 219.5
              },
              {
                "name": "Under",
                "price": -108,
                "point": 219.5
              }
            ]
          }
        ]
      },
      {
        "key": "betonlineag",
        "title": "BetOnline.ag",
        "last_update": "2025-12-31T01:40:09Z",
        "markets": [
          {
            "key": "totals",
            "last_update": "2025-12-31T01:40:09Z",
            "outcomes": [
              {
                "name": "Over",
                "price": -110,
                "point": 220.0
              },
              {
                "name": "Under",
                "price": -110,
                "point": 220.0
              }
            ]
          }
        ]
      },
      {
        "key": "lowvig",
        "title": "LowVig.ag",
        "last_update": "2025-12-31T01:40:36Z",
        "markets": [
          {
            "key": "totals",
            "last_update": "2025-12-31T01:40:36Z",
            "outcomes": [
              {
                "name": "Over",
                "price": -107,
                "point": 220.0
              },
              {
                "name": "Under",
                "price": -107,
                "point": 220.0
              }
            ]
          }
        ]
      },
      {
        "key": "draftkings",
        "title": "DraftKings",
        "last_update": "2025-12-31T01:40:35Z",
        "markets": [
          {
            "key": "totals",
            "last_update": "2025-12-31T01:40:35Z",
            "outcomes": [
              {
                "name": "Over",
                "price": -112,
                "point": 219.5
              },
              {
                "name": "Under",
                "price": -108,
                "point": 219.5
              }
            ]
          }
        ]
      },
      {
        "key": "mybookieag",
        "title": "MyBookie.ag",
        "last_update": "2025-12-31T01:39:04Z",
        "markets": [
          {
            "key": "totals",
            "last_update": "2025-12-31T01:39:04Z",
            "outcomes": [
              {
                "name": "Over",
                "price": -110,
                "point": 220.0
              },
              {
                "name": "Under",
                "price": -110,
                "point": 220.0
              }
            ]
          }
        ]
      },
      {
        "key": "fanatics",
        "title": "Fanatics",
        "last_update": "2025-12-31T01:40:35Z",
        "markets": [
          {
            "key": "totals",
            "last_update": "2025-12-31T01:40:35Z",
            "outcomes": [
              {
                "name": "Over",
                "price": -110,
                "point": 219.5
              },
              {
                "name": "Under",
                "price": -110,
                "point": 219.5
              }
            ]
          }
        ]
      },
      {
        "key": "williamhill_us",
        "title": "Caesars",
        "last_update": "2025-12-31T01:37:44Z",
        "markets": [
          {
            "key": "totals",
            "last_update": "2025-12-31T01:37:44Z",
            "outcomes": [
              {
                "name": "Over",
                "price": -110,
                "point": 220.0
              },
              {
                "name": "Under",
                "price": -110,
                "point": 220.0
              }
            ]
          }
        ]
      },
      {
        "key": "bovada",
        "title": "Bovada",
        "last_update": "2025-12-31T01:40:35Z",
        "markets": [
          {
            "key": "totals",
            "last_update": "2025-12-31T01:40:35Z",
            "outcomes": [
              {
                "name": "Over",
                "price": -110,
                "point": 219.5
              },
              {
                "name": "Under",
                "price": -110,
                "point": 219.5
              }
            ]
          }
        ]
      },
      {
        "key": "betmgm",
        "title": "BetMGM",
        "last_update": "2025-12-31T01:40:20Z",
        "markets": [
          {
            "key": "totals",
            "last_update": "2025-12-31T01:40:20Z",
            "outcomes": [
              {
                "name": "Over",
                "price": -105,
                "point": 220.5
              },
              {
                "name": "Under",
                "price": -115,
                "point": 220.5
              }
            ]
          }
        ]
      },
      {
        "key": "betus",
        "title": "BetUS",
        "last_update": "2025-12-31T01:40:49Z",
        "markets": [
          {
            "key": "totals",
            "last_update": "2025-12-31T01:40:49Z",
            "outcomes": [
              {
                "name": "Over",
                "price": -110,
                "point": 219.5
              },
              {
                "name": "Under",
                "price": -110,
                "point": 219.5
              }
            ]
          }
        ]
      }
    ]
  },
  {
    "id": "d4543fb033b06b74cc32ab5c457e5bf1",
    "sport_key": "basketball_nba",
    "sport_title": "NBA",
    "commence_time": "2025-12-31T18:10:00Z",
    "home_team": "Charlotte Hornets",
    "away_team": "Golden State Warriors",
    "bookmakers": [
      {
        "key": "fanduel",
        "title": "FanDuel",
        "last_update": "2025-12-31T01:40:36Z",
        "markets": [
          {
            "key": "totals",
            "last_update": "2025-12-31T01:40:36Z",
            "outcomes": [
              {
                "name": "Over",
                "price": -106,
                "point": 233.5
              },
              {
                "name": "Under",
                "price": -114,
                "point": 233.5
              }
            ]
          }
        ]
      },
      {
        "key": "fanatics",
        "title": "Fanatics",
        "last_update": "2025-12-31T01:40:35Z",
        "markets": [
          {
            "key": "totals",
            "last_update": "2025-12-31T01:40:35Z",
            "outcomes": [
              {
                "name": "Over",
                "price": -110,
                "point": 233.0
              },
              {
                "name": "Under",
                "price": -110,
                "point": 233.0
              }
            ]
          }
        ]
      }
    ]
  },
  {
    "id": "a8689888bf88aea46eb8e5e4816e0a8b",
    "sport_key": "basketball_nba",
    "sport_title": "NBA",
    "commence_time": "2025-12-31T20:10:00Z",
    "home_team": "Atlanta Hawks",
    "away_team": "Minnesota Timberwolves",
    "bookmakers": [
      {
        "key": "fanduel",
        "title": "FanDuel",
        "last_update": "2025-12-31T01:40:36Z",
        "markets": [
          {
            "key": "totals",
            "last_update": "2025-12-31T01:40:36Z",
            "outcomes": [
              {
                "name": "Over",
                "price": -110,
                "point": 243.5
              },
              {
                "name": "Under",
                "price": -110,
                "point": 243.5
              }
            ]
          }
        ]
      }
    ]
  },
  {
    "id": "2c79a786a51636721f6f09b683b6e428",
    "sport_key": "basketball_nba",
    "sport_title": "NBA",
    "commence_time": "2025-12-31T20:10:00Z",
    "home_team": "Indiana Pacers",
    "away_team": "Orlando Magic",
    "bookmakers": [
      {
        "key": "fanduel",
        "title": "FanDuel",
        "last_update": "2025-12-31T01:40:36Z",
        "markets": [
          {
            "key": "totals",
            "last_update": "2025-12-31T01:40:36Z",
            "outcomes": [
              {
                "name": "Over",
                "price": -105,
                "point": 225.5
              },
              {
                "name": "Under",
                "price": -115,
                "point": 225.5
              }
            ]
          }
        ]
      }
    ]
  },
  {
    "id": "aef966e3de9dde21d6030e301e8e59b3",
    "sport_key": "basketball_nba",
    "sport_title": "NBA",
    "commence_time": "2025-12-31T20:40:00Z",
    "home_team": "Cleveland Cavaliers",
    "away_team": "Phoenix Suns",
    "bookmakers": [
      {
        "key": "fanduel",
        "title": "FanDuel",
        "last_update": "2025-12-31T01:40:36Z",
        "markets": [
          {
            "key": "totals",
            "last_update": "2025-12-31T01:40:36Z",
            "outcomes": [
              {
                "name": "Over",
                "price": -105,
                "point": 236.5
              },
              {
                "name": "Under",
                "price": -115,
                "point": 236.5
              }
            ]
          }
        ]
      },
      {
        "key": "lowvig",
        "title": "LowVig.ag",
        "last_update": "2025-12-31T01:40:36Z",
        "markets": [
          {
            "key": "totals",
            "last_update": "2025-12-31T01:40:36Z",
            "outcomes": [
              {
                "name": "Over",
                "price": -107,
                "point": 237.0
              },
              {
                "name": "Under",
                "price": -107,
                "point": 237.0
              }
            ]
          }
        ]
      },
      {
        "key": "betonlineag",
        "title": "BetOnline.ag",
        "last_update": "2025-12-31T01:40:09Z",
        "markets": [
          {
            "key": "totals",
            "last_update": "2025-12-31T01:40:09Z",
            "outcomes": [
              {
                "name": "Over",
                "price": -110,
                "point": 237.0
              },
              {
                "name": "Under",
                "price": -110,
                "point": 237.0
              }
            ]
          }
        ]
      },
      {
        "key": "draftkings",
        "title": "DraftKings",
        "last_update": "2025-12-31T01:40:35Z",
        "markets": [
          {
            "key": "totals",
            "last_update": "2025-12-31T01:40:35Z",
            "outcomes": [
              {
                "name": "Over",
                "price": -110,
                "point": 235.5
              },
              {
                "name": "Under",
                "price": -110,
                "point": 235.5
              }
            ]
          }
        ]
      },
      {
        "key": "williamhill_us",
        "title": "Caesars",
        "last_update": "2025-12-31T01:37:44Z",
        "markets": [
          {
            "key": "totals",
            "last_update": "2025-12-31T01:37:44Z",
            "outcomes": [
              {
                "name": "Over",
                "price": -115,
                "point": 236.5
              },
              {
                "name": "Under",
                "price": -105,
                "point": 236.5
              }
            ]
          }
        ]
      },
      {
        "key": "fanatics",
        "title": "Fanatics",
        "last_update": "2025-12-31T01:40:35Z",
        "markets": [
          {
            "key": "totals",
            "last_update": "2025-12-31T01:40:35Z",
            "outcomes": [
              {
                "name": "Over",
                "price": -110,
                "point": 236.0
              },
              {
                "name": "Under",
                "price": -110,
                "point": 236.0
              }
            ]
          }
        ]
      }
    ]
  },
  {
    "id": "b0362ad1064234a482e1672ab3d1c4eb",
    "sport_key": "basketball_nba",
    "sport_title": "NBA",
    "commence_time": "2026-01-01T00:10:00Z",
    "home_team": "Chicago Bulls",
    "away_team": "New Orleans Pelicans",
    "bookmakers": [
      {
        "key": "fanduel",
        "title": "FanDuel",
        "last_update": "2025-12-31T01:40:36Z",
        "markets": [
          {
            "key": "totals",
            "last_update": "2025-12-31T01:40:36Z",
            "outcomes": [
              {
                "name": "Over",
                "price": -112,
                "point": 246.5
              },
              {
                "name": "Under",
                "price": -108,
                "point": 246.5
              }
            ]
          }
        ]
      },
      {
        "key": "fanatics",
        "title": "Fanatics",
        "last_update": "2025-12-31T01:40:35Z",
        "markets": [
          {
            "key": "totals",
            "last_update": "2025-12-31T01:40:35Z",
            "outcomes": [
              {
                "name": "Over",
                "price": -110,
                "point": 247.0
              },
              {
                "name": "Under",
                "price": -110,
                "point": 247.0
              }
            ]
          }
        ]
      }
    ]
  },
  {
    "id": "da1f30e39aa879eeca4dcc42cde3cfbe",
    "sport_key": "basketball_nba",
    "sport_title": "NBA",
    "commence_time": "2026-01-01T00:10:00Z",
    "home_team": "San Antonio Spurs",
    "away_team": "New York Knicks",
    "bookmakers": [
      {
        "key": "fanduel",
        "title": "FanDuel",
        "last_update": "2025-12-31T01:40:36Z",
        "markets": [
          {
            "key": "totals",
            "last_update": "2025-12-31T01:40:36Z",
            "outcomes": [
              {
                "name": "Over",
                "price": -114,
                "point": 236.5
              },
              {
                "name": "Under",
                "price": -106,
                "point": 236.5
              }
            ]
          }
        ]
      },
      {
        "key": "fanatics",
        "title": "Fanatics",
        "last_update": "2025-12-31T01:40:35Z",
        "markets": [
          {
            "key": "totals",
            "last_update": "2025-12-31T01:40:35Z",
            "outcomes": [
              {
                "name": "Over",
                "price": -110,
                "point": 236.5
              },
              {
                "name": "Under",
                "price": -110,
                "point": 236.5
              }
            ]
          }
        ]
      },
      {
        "key": "lowvig",
        "title": "LowVig.ag",
        "last_update": "2025-12-31T01:40:36Z",
        "markets": [
          {
            "key": "totals",
            "last_update": "2025-12-31T01:40:36Z",
            "outcomes": [
              {
                "name": "Over",
                "price": -113,
                "point": 236.5
              },
              {
                "name": "Under",
                "price": -102,
                "point": 236.5
              }
            ]
          }
        ]
      },
      {
        "key": "betonlineag",
        "title": "BetOnline.ag",
        "last_update": "2025-12-31T01:40:09Z",
        "markets": [
          {
            "key": "totals",
            "last_update": "2025-12-31T01:40:09Z",
            "outcomes": [
              {
                "name": "Over",
                "price": -115,
                "point": 236.5
              },
              {
                "name": "Under",
                "price": -105,
                "point": 236.5
              }
            ]
          }
        ]
      },
      {
        "key": "draftkings",
        "title": "DraftKings",
        "last_update": "2025-12-31T01:40:35Z",
        "markets": [
          {
            "key": "totals",
            "last_update": "2025-12-31T01:40:35Z",
            "outcomes": [
              {
                "name": "Over",
                "price": -110,
                "point": 236.5
              },
              {
                "name": "Under",
                "price": -110,
                "point": 236.5
              }
            ]
          }
        ]
      },
      {
        "key": "williamhill_us",
        "title": "Caesars",
        "last_update": "2025-12-31T01:37:44Z",
        "markets": [
          {
            "key": "totals",
            "last_update": "2025-12-31T01:37:44Z",
            "outcomes": [
              {
                "name": "Over",
                "price": -115,
                "point": 236.5
              },
              {
                "name": "Under",
                "price": -105,
                "point": 236.5
              }
            ]
          }
        ]
      }
    ]
  },
  {
    "id": "95fe64ebf512b70546be9938007b1a8c",
    "sport_key": "basketball_nba",
    "sport_title": "NBA",
    "commence_time": "2026-01-01T00:40:00Z",
    "home_team": "Toronto Raptors",
    "away_team": "Denver Nuggets",
    "bookmakers": [
      {
        "key": "fanduel",
        "title": "FanDuel",
        "last_update": "2025-12-31T01:40:36Z",
        "markets": [
          {
            "key": "totals",
            "last_update": "2025-12-31T01:40:36Z",
            "outcomes": [
              {
                "name": "Over",
                "price": -108,
                "point": 225.5
              },
              {
                "name": "Under",
                "price": -112,
                "point": 225.5
              }
            ]
          }
        ]
      },
      {
        "key": "lowvig",
        "title": "LowVig.ag",
        "last_update": "2025-12-31T01:40:36Z",
        "markets": [
          {
            "key": "totals",
            "last_update": "2025-12-31T01:40:36Z",
            "outcomes": [
              {
                "name": "Over",
                "price": -107,
                "point": 224.5
              },
              {
                "name": "Under",
                "price": -107,
                "point": 224.5
              }
            ]
          }
        ]
      },
      {
        "key": "betonlineag",
        "title": "BetOnline.ag",
        "last_update": "2025-12-31T01:40:09Z",
        "markets": [
          {
            "key": "totals",
            "last_update": "2025-12-31T01:40:09Z",
            "outcomes": [
              {
                "name": "Over",
                "price": -110,
                "point": 224.5
              },
              {
                "name": "Under",
                "price": -110,
                "point": 224.5
              }
            ]
          }
        ]
      },
      {
        "key": "draftkings",
        "title": "DraftKings",
        "last_update": "2025-12-31T01:40:35Z",
        "markets": [
          {
            "key": "totals",
            "last_update": "2025-12-31T01:40:35Z",
            "outcomes": [
              {
                "name": "Over",
                "price": -110,
                "point": 224.5
              },
              {
                "name": "Under",
                "price": -110,
                "point": 224.5
              }
            ]
          }
        ]
      },
      {
        "key": "williamhill_us",
        "title": "Caesars",
        "last_update": "2025-12-31T01:37:44Z",
        "markets": [
          {
            "key": "totals",
            "last_update": "2025-12-31T01:37:44Z",
            "outcomes": [
              {
                "name": "Over",
                "price": -110,
                "point": 225.0
              },
              {
                "name": "Under",
                "price": -110,
                "point": 225.0
              }
            ]
          }
        ]
      }
    ]
  },
  {
    "id": "3267add7bc04a110d6596463f7c8a495",
    "sport_key": "basketball_nba",
    "sport_title": "NBA",
    "commence_time": "2026-01-01T01:10:00Z",
    "home_team": "Milwaukee Bucks",
    "away_team": "Washington Wizards",
    "bookmakers": [
      {
        "key": "fanduel",
        "title": "FanDuel",
        "last_update": "2025-12-31T01:40:36Z",
        "markets": [
          {
            "key": "totals",
            "last_update": "2025-12-31T01:40:36Z",
            "outcomes": [
              {
                "name": "Over",
                "price": -106,
                "point": 231.5
              },
              {
                "name": "Under",
                "price": -114,
                "point": 231.5
              }
            ]
          }
        ]
      },
      {
        "key": "lowvig",
        "title": "LowVig.ag",
        "last_update": "2025-12-31T01:40:36Z",
        "markets": [
          {
            "key": "totals",
            "last_update": "2025-12-31T01:40:36Z",
            "outcomes": [
              {
                "name": "Over",
                "price": -102,
                "point": 231.5
              },
              {
                "name": "Under",
                "price": -113,
                "point": 231.5
              }
            ]
          }
        ]
      },
      {
        "key": "betonlineag",
        "title": "BetOnline.ag",
        "last_update": "2025-12-31T01:40:09Z",
        "markets": [
          {
            "key": "totals",
            "last_update": "2025-12-31T01:40:09Z",
            "outcomes": [
              {
                "name": "Over",
                "price": -105,
                "point": 231.5
              },
              {
                "name": "Under",
                "price": -115,
                "point": 231.5
              }
            ]
          }
        ]
      },
      {
        "key": "draftkings",
        "title": "DraftKings",
        "last_update": "2025-12-31T01:40:35Z",
        "markets": [
          {
            "key": "totals",
            "last_update": "2025-12-31T01:40:35Z",
            "outcomes": [
              {
                "name": "Over",
                "price": -110,
                "point": 232.5
              },
              {
                "name": "Under",
                "price": -110,
                "point": 232.5
              }
            ]
          }
        ]
      },
      {
        "key": "williamhill_us",
        "title": "Caesars",
        "last_update": "2025-12-31T01:37:44Z",
        "markets": [
          {
            "key": "totals",
            "last_update": "2025-12-31T01:37:44Z",
            "outcomes": [
              {
                "name": "Over",
                "price": -105,
                "point": 232.0
              },
              {
                "name": "Under",
                "price": -115,
                "point": 232.0
              }
            ]
          }
        ]
      }
    ]
  },
  {
    "id": "08d7e57dd2b795455b1abb447f608705",
    "sport_key": "basketball_nba",
    "sport_title": "NBA",
    "commence_time": "2026-01-01T01:10:00Z",
    "home_team": "Oklahoma City Thunder",
    "away_team": "Portland Trail Blazers",
    "bookmakers": [
      {
        "key": "fanduel",
        "title": "FanDuel",
        "last_update": "2025-12-31T01:40:36Z",
        "markets": [
          {
            "key": "totals",
            "last_update": "2025-12-31T01:40:36Z",
            "outcomes": [
              {
                "name": "Over",
                "price": -106,
                "point": 234.5
              },
              {
                "name": "Under",
                "price": -114,
                "point": 234.5
              }
            ]
          }
        ]
      },
      {
        "key": "betonlineag",
        "title": "BetOnline.ag",
        "last_update": "2025-12-31T01:40:09Z",
        "markets": [
          {
            "key": "totals",
            "last_update": "2025-12-31T01:40:09Z",
            "outcomes": [
              {
                "name": "Over",
                "price": -110,
                "point": 234.0
              },
              {
                "name": "Under",
                "price": -110,
                "point": 234.0
              }
            ]
          }
        ]
      },
      {
        "key": "lowvig",
        "title": "LowVig.ag",
        "last_update": "2025-12-31T01:40:36Z",
        "markets": [
          {
            "key": "totals",
            "last_update": "2025-12-31T01:40:36Z",
            "outcomes": [
              {
                "name": "Over",
                "price": -107,
                "point": 234.0
              },
              {
                "name": "Under",
                "price": -107,
                "point": 234.0
              }
            ]
          }
        ]
      },
      {
        "key": "draftkings",
        "title": "DraftKings",
        "last_update": "2025-12-31T01:40:35Z",
        "markets": [
          {
            "key": "totals",
            "last_update": "2025-12-31T01:40:35Z",
            "outcomes": [
              {
                "name": "Over",
                "price": -110,
                "point": 233.5
              },
              {
                "name": "Under",
                "price": -110,
                "point": 233.5
              }
            ]
          }
        ]
      },
      {
        "key": "williamhill_us",
        "title": "Caesars",
        "last_update": "2025-12-31T01:37:44Z",
        "markets": [
          {
            "key": "totals",
            "last_update": "2025-12-31T01:37:44Z",
            "outcomes": [
              {
                "name": "Over",
                "price": -110,
                "point": 234.0
              },
              {
                "name": "Under",
                "price": -110,
                "point": 234.0
              }
            ]
          }
        ]
      }
    ]
  }
]